{
  "spaceBetweenLegends": [
    { "id": 1000, "leftToothId": 18, "rightToothId": 17, "dynamicDesign": null, "color": null, "findings": []},
    { "id": 1001, "leftToothId": 17, "rightToothId": 16, "dynamicDesign": null, "color": null, "findings": []},
    { "id": 1002, "leftToothId": 16, "rightToothId": 15, "dynamicDesign": null, "color": null, "findings": [] },
    { "id": 1003, "leftToothId": 15, "rightToothId": 14, "dynamicDesign": null, "color": null, "findings": [] },
    { "id": 1004, "leftToothId": 14, "rightToothId": 13, "dynamicDesign": null, "color": null, "findings": [] },
    { "id": 1005, "leftToothId": 13, "rightToothId": 12, "dynamicDesign": null, "color": null, "findings": [] },
    { "id": 1006, "leftToothId": 12, "rightToothId": 11, "dynamicDesign": null, "color": null, "findings": [] },
    { "id": 1007, "leftToothId": 11, "rightToothId": 21, "dynamicDesign": null, "color": null, "findings": [] },
    { "id": 1008, "leftToothId": 21, "rightToothId": 22, "dynamicDesign": null, "color": null, "findings": [] },
    { "id": 1009, "leftToothId": 22, "rightToothId": 23, "dynamicDesign": null, "color": null, "findings": [] },
    { "id": 1010, "leftToothId": 23, "rightToothId": 24, "dynamicDesign": null, "color": null, "findings": [] },
    { "id": 1011, "leftToothId": 24, "rightToothId": 25, "dynamicDesign": null, "color": null, "findings": [] },
    { "id": 1012, "leftToothId": 25, "rightToothId": 26, "dynamicDesign": null, "color": null,"findings": [] },
    { "id": 1013, "leftToothId": 26, "rightToothId": 27, "dynamicDesign": null, "color": null, "findings": [] },
    { "id": 1014, "leftToothId": 27, "rightToothId": 28, "dynamicDesign": null, "color": null,"findings": [] }
  ],
  "intermediateSpaceOnTheCanvasOfFinding1": [
    { "id": 100000, "leftToothId": 18, "rightToothId": 17, "dynamicDesign": null, "color": null, "findings": [] },
    { "id": 100001, "leftToothId": 17, "rightToothId": 16, "dynamicDesign": null, "color": null,"findings": [] },
    { "id": 100002, "leftToothId": 16, "rightToothId": 15, "dynamicDesign": null, "color": null, "findings": [] },
    { "id": 100003, "leftToothId": 15, "rightToothId": 14, "dynamicDesign": null, "color": null, "findings": [] },
    { "id": 100004, "leftToothId": 14, "rightToothId": 13, "dynamicDesign": null, "color": null, "findings": [] },
    { "id": 100005, "leftToothId": 13, "rightToothId": 12, "dynamicDesign": null, "color": null, "findings": [] },
    { "id": 100006, "leftToothId": 12, "rightToothId": 11, "dynamicDesign": null, "color": null, "findings": [] },
    { "id": 100007, "leftToothId": 11, "rightToothId": 21, "dynamicDesign": null, "color": null, "findings": [] },
    { "id": 100008, "leftToothId": 21, "rightToothId": 22, "dynamicDesign": null, "color": null, "findings": [] },
    { "id": 100009, "leftToothId": 22, "rightToothId": 23, "dynamicDesign": null, "color": null, "findings": [] },
    { "id": 100010, "leftToothId": 23, "rightToothId": 24, "dynamicDesign": null, "color": null, "findings": [] },
    { "id": 100011, "leftToothId": 24, "rightToothId": 25, "dynamicDesign": null, "color": null, "findings": [] },
    { "id": 100012, "leftToothId": 25, "rightToothId": 26, "dynamicDesign": null, "color": null, "findings": [] },
    { "id": 100013, "leftToothId": 26, "rightToothId": 27, "dynamicDesign": null, "color": null,"findings": [] },
    { "id": 100014, "leftToothId": 27, "rightToothId": 28, "dynamicDesign": null, "color": null,"findings": [] }
  ],
  "intermediateSpaceOnTheCanvasOfFinding2": [
    { "id": 200000, "leftToothId": 18, "rightToothId": 17, "dynamicDesign": null, "color": null, "findings": [] },
    { "id": 200001, "leftToothId": 17, "rightToothId": 16, "dynamicDesign": null, "color": null,"findings": [] },
    { "id": 200002, "leftToothId": 16, "rightToothId": 15, "dynamicDesign": null, "color": null, "findings": [] },
    { "id": 200003, "leftToothId": 15, "rightToothId": 14, "dynamicDesign": null, "color": null, "findings": [] },
    { "id": 200004, "leftToothId": 14, "rightToothId": 13, "dynamicDesign": null, "color": null, "findings": [] },
    { "id": 200005, "leftToothId": 13, "rightToothId": 12, "dynamicDesign": null, "color": null, "findings": [] },
    { "id": 200006, "leftToothId": 12, "rightToothId": 11, "dynamicDesign": null, "color": null, "findings": [] },
    { "id": 200007, "leftToothId": 11, "rightToothId": 21, "dynamicDesign": null, "color": null, "findings": [] },
    { "id": 200008, "leftToothId": 21, "rightToothId": 22, "dynamicDesign": null, "color": null, "findings": [] },
    { "id": 200009, "leftToothId": 22, "rightToothId": 23, "dynamicDesign": null, "color": null, "findings": [] },
    { "id": 200010, "leftToothId": 23, "rightToothId": 24, "dynamicDesign": null, "color": null, "findings": [] },
    { "id": 200011, "leftToothId": 24, "rightToothId": 25, "dynamicDesign": null, "color": null, "findings": [] },
    { "id": 200012, "leftToothId": 25, "rightToothId": 26, "dynamicDesign": null, "color": null, "findings": [] },
    { "id": 200013, "leftToothId": 26, "rightToothId": 27, "dynamicDesign": null, "color": null, "findings": [] },
    { "id": 200014, "leftToothId": 27, "rightToothId": 28, "dynamicDesign": null, "color": null, "findings": [] }
  ],
  "intermediateSpaceOnTheCanvasOfFinding6": [
    { "id": 600000, "leftToothId": 18, "rightToothId": 17, "dynamicDesign": null, "color": null, "findings": [] },
    { "id": 600001, "leftToothId": 17, "rightToothId": 16, "dynamicDesign": null, "color": null,"findings": [] },
    { "id": 600002, "leftToothId": 16, "rightToothId": 15, "dynamicDesign": null, "color": null, "findings": [] },
    { "id": 600003, "leftToothId": 15, "rightToothId": 14, "dynamicDesign": null, "color": null, "findings": [] },
    { "id": 600004, "leftToothId": 14, "rightToothId": 13, "dynamicDesign": null, "color": null, "findings": [] },
    { "id": 600005, "leftToothId": 13, "rightToothId": 12, "dynamicDesign": null, "color": null, "findings": [] },
    { "id": 600006, "leftToothId": 12, "rightToothId": 11, "dynamicDesign": null, "color": null, "findings": [] },
    { "id": 600007, "leftToothId": 11, "rightToothId": 21, "dynamicDesign": null, "color": null, "findings": [] },
    { "id": 600008, "leftToothId": 21, "rightToothId": 22, "dynamicDesign": null, "color": null, "findings": [] },
    { "id": 600009, "leftToothId": 22, "rightToothId": 23, "dynamicDesign": null, "color": null, "findings": [] },
    { "id": 600010, "leftToothId": 23, "rightToothId": 24, "dynamicDesign": null, "color": null, "findings": [] },
    { "id": 600011, "leftToothId": 24, "rightToothId": 25, "dynamicDesign": null, "color": null, "findings": [] },
    { "id": 600012, "leftToothId": 25, "rightToothId": 26, "dynamicDesign": null, "color": null, "findings": [] },
    { "id": 600013, "leftToothId": 26, "rightToothId": 27, "dynamicDesign": null, "color": null, "findings": [] },
    { "id": 600014, "leftToothId": 27, "rightToothId": 28, "dynamicDesign": null, "color": null, "findings": [] }
  ],
  "intermediateSpaceOnTheCanvasOfFinding7": [
    { "id": 700000, "leftToothId": 18, "rightToothId": 17, "dynamicDesign": null, "color": null, "findings": [] },
    { "id": 700001, "leftToothId": 17, "rightToothId": 16, "dynamicDesign": null, "color": null,"findings": [] },
    { "id": 700002, "leftToothId": 16, "rightToothId": 15, "dynamicDesign": null, "color": null, "findings": [] },
    { "id": 700003, "leftToothId": 15, "rightToothId": 14, "dynamicDesign": null, "color": null, "findings": [] },
    { "id": 700004, "leftToothId": 14, "rightToothId": 13, "dynamicDesign": null, "color": null, "findings": [] },
    { "id": 700005, "leftToothId": 13, "rightToothId": 12, "dynamicDesign": null, "color": null, "findings": [] },
    { "id": 700006, "leftToothId": 12, "rightToothId": 11, "dynamicDesign": null, "color": null, "findings": [] },
    { "id": 700007, "leftToothId": 11, "rightToothId": 21, "dynamicDesign": null, "color": null, "findings": [] },
    { "id": 700008, "leftToothId": 21, "rightToothId": 22, "dynamicDesign": null, "color": null, "findings": [] },
    { "id": 700009, "leftToothId": 22, "rightToothId": 23, "dynamicDesign": null, "color": null, "findings": [] },
    { "id": 700010, "leftToothId": 23, "rightToothId": 24, "dynamicDesign": null, "color": null, "findings": [] },
    { "id": 700011, "leftToothId": 24, "rightToothId": 25, "dynamicDesign": null, "color": null, "findings": [] },
    { "id": 700012, "leftToothId": 25, "rightToothId": 26, "dynamicDesign": null, "color": null, "findings": [] },
    { "id": 700013, "leftToothId": 26, "rightToothId": 27, "dynamicDesign": null, "color": null, "findings": [] },
    { "id": 700014, "leftToothId": 27, "rightToothId": 28, "dynamicDesign": null, "color": null, "findings": [] }
  ],
  "intermediateSpaceOnTheCanvasOfFinding24": [
    { "id": 2400000, "leftToothId": 18, "rightToothId": 17, "dynamicDesign": null, "color": null, "findings": [] },
    { "id": 2400001, "leftToothId": 17, "rightToothId": 16, "dynamicDesign": null, "color": null, "findings": [] },
    { "id": 2400002, "leftToothId": 16, "rightToothId": 15, "dynamicDesign": null, "color": null, "findings": [] },
    { "id": 2400003, "leftToothId": 15, "rightToothId": 14, "dynamicDesign": null, "color": null, "findings": [] },
    { "id": 2400004, "leftToothId": 14, "rightToothId": 13, "dynamicDesign": null, "color": null, "findings": [] },
    { "id": 2400005, "leftToothId": 13, "rightToothId": 12, "dynamicDesign": null, "color": null, "findings": [] },
    { "id": 2400006, "leftToothId": 12, "rightToothId": 11, "dynamicDesign": null, "color": null, "findings": [] },
    { "id": 2400007, "leftToothId": 11, "rightToothId": 21, "dynamicDesign": null, "color": null, "findings": [] },
    { "id": 2400008, "leftToothId": 21, "rightToothId": 22, "dynamicDesign": null, "color": null, "findings": [] },
    { "id": 2400009, "leftToothId": 22, "rightToothId": 23, "dynamicDesign": null, "color": null, "findings": [] },
    { "id": 2400010, "leftToothId": 23, "rightToothId": 24, "dynamicDesign": null, "color": null, "findings": [] },
    { "id": 2400011, "leftToothId": 24, "rightToothId": 25, "dynamicDesign": null, "color": null, "findings": [] },
    { "id": 2400012, "leftToothId": 25, "rightToothId": 26, "dynamicDesign": null, "color": null, "findings": [] },
    { "id": 2400013, "leftToothId": 26, "rightToothId": 27, "dynamicDesign": null, "color": null, "findings": [] },
    { "id": 2400014, "leftToothId": 27, "rightToothId": 28, "dynamicDesign": null, "color": null, "findings": [] }
  ],
  "intermediateSpaceOnTheCanvasOfFinding25": [
    { "id": 2500000, "leftToothId": 18, "rightToothId": 17, "dynamicDesign": null, "color": null, "findings": [] },
    { "id": 2500001, "leftToothId": 17, "rightToothId": 16, "dynamicDesign": null, "color": null, "findings": [] },
    { "id": 2500002, "leftToothId": 16, "rightToothId": 15, "dynamicDesign": null, "color": null, "findings": [] },
    { "id": 2500003, "leftToothId": 15, "rightToothId": 14, "dynamicDesign": null, "color": null, "findings": [] },
    { "id": 2500004, "leftToothId": 14, "rightToothId": 13, "dynamicDesign": null, "color": null, "findings": [] },
    { "id": 2500005, "leftToothId": 13, "rightToothId": 12, "dynamicDesign": null, "color": null, "findings": [] },
    { "id": 2500006, "leftToothId": 12, "rightToothId": 11, "dynamicDesign": null, "color": null, "findings": [] },
    { "id": 2500007, "leftToothId": 11, "rightToothId": 21, "dynamicDesign": null, "color": null, "findings": [] },
    { "id": 2500008, "leftToothId": 21, "rightToothId": 22, "dynamicDesign": null, "color": null, "findings": [] },
    { "id": 2500009, "leftToothId": 22, "rightToothId": 23, "dynamicDesign": null, "color": null, "findings": [] },
    { "id": 2500010, "leftToothId": 23, "rightToothId": 24, "dynamicDesign": null, "color": null, "findings": [] },
    { "id": 2500011, "leftToothId": 24, "rightToothId": 25, "dynamicDesign": null, "color": null, "findings": [] },
    { "id": 2500012, "leftToothId": 25, "rightToothId": 26, "dynamicDesign": null, "color": null, "findings": [] },
    { "id": 2500013, "leftToothId": 26, "rightToothId": 27, "dynamicDesign": null, "color": null, "findings": [] },
    { "id": 2500014, "leftToothId": 27, "rightToothId": 28, "dynamicDesign": null, "color": null, "findings": [] }
  ],
  "intermediateSpaceOnTheCanvasOfFinding26": [
    { "id": 2600000, "leftToothId": 18, "rightToothId": 17, "dynamicDesign": null, "color": null, "findings": [] },
    { "id": 2600001, "leftToothId": 17, "rightToothId": 16, "dynamicDesign": null, "color": null, "findings": [] },
    { "id": 2600002, "leftToothId": 16, "rightToothId": 15, "dynamicDesign": null, "color": null, "findings": [] },
    { "id": 2600003, "leftToothId": 15, "rightToothId": 14, "dynamicDesign": null, "color": null, "findings": [] },
    { "id": 2600004, "leftToothId": 14, "rightToothId": 13, "dynamicDesign": null, "color": null, "findings": [] },
    { "id": 2600005, "leftToothId": 13, "rightToothId": 12, "dynamicDesign": null, "color": null, "findings": [] },
    { "id": 2600006, "leftToothId": 12, "rightToothId": 11, "dynamicDesign": null, "color": null, "findings": [] },
    { "id": 2600007, "leftToothId": 11, "rightToothId": 21, "dynamicDesign": null, "color": null, "findings": [] },
    { "id": 2600008, "leftToothId": 21, "rightToothId": 22, "dynamicDesign": null, "color": null, "findings": [] },
    { "id": 2600009, "leftToothId": 22, "rightToothId": 23, "dynamicDesign": null, "color": null, "findings": [] },
    { "id": 2600010, "leftToothId": 23, "rightToothId": 24, "dynamicDesign": null, "color": null, "findings": [] },
    { "id": 2600011, "leftToothId": 24, "rightToothId": 25, "dynamicDesign": null, "color": null, "findings": [] },
    { "id": 2600012, "leftToothId": 25, "rightToothId": 26, "dynamicDesign": null, "color": null, "findings": [] },
    { "id": 2600013, "leftToothId": 26, "rightToothId": 27, "dynamicDesign": null, "color": null, "findings": [] },
    { "id": 2600014, "leftToothId": 27, "rightToothId": 28, "dynamicDesign": null, "color": null, "findings": [] }
  ],
  "intermediateSpaceOnTheCanvasOfFinding30": [
    { "id": 3000000, "leftToothId": 18, "rightToothId": 17, "dynamicDesign": null, "color": null, "findings": [] },
    { "id": 3000001, "leftToothId": 17, "rightToothId": 16, "dynamicDesign": null, "color": null, "findings": [] },
    { "id": 3000002, "leftToothId": 16, "rightToothId": 15, "dynamicDesign": null, "color": null, "findings": [] },
    { "id": 3000003, "leftToothId": 15, "rightToothId": 14, "dynamicDesign": null, "color": null, "findings": [] },
    { "id": 3000004, "leftToothId": 14, "rightToothId": 13, "dynamicDesign": null, "color": null, "findings": [] },
    { "id": 3000005, "leftToothId": 13, "rightToothId": 12, "dynamicDesign": null, "color": null, "findings": [] },
    { "id": 3000006, "leftToothId": 12, "rightToothId": 11, "dynamicDesign": null, "color": null, "findings": [] },
    { "id": 3000007, "leftToothId": 11, "rightToothId": 21, "dynamicDesign": null, "color": null, "findings": [] },
    { "id": 3000008, "leftToothId": 21, "rightToothId": 22, "dynamicDesign": null, "color": null, "findings": [] },
    { "id": 3000009, "leftToothId": 22, "rightToothId": 23, "dynamicDesign": null, "color": null, "findings": [] },
    { "id": 3000010, "leftToothId": 23, "rightToothId": 24, "dynamicDesign": null, "color": null, "findings": [] },
    { "id": 3000011, "leftToothId": 24, "rightToothId": 25, "dynamicDesign": null, "color": null, "findings": [] },
    { "id": 3000012, "leftToothId": 25, "rightToothId": 26, "dynamicDesign": null, "color": null, "findings": [] },
    { "id": 3000013, "leftToothId": 26, "rightToothId": 27, "dynamicDesign": null, "color": null, "findings": [] },
    { "id": 3000014, "leftToothId": 27, "rightToothId": 28, "dynamicDesign": null, "color": null, "findings": [] }
  ],
  "intermediateSpaceOnTheCanvasOfFinding31": [
    { "id": 3100000, "leftToothId": 18, "rightToothId": 17, "dynamicDesign": null, "color": null, "findings": [] },
    { "id": 3100001, "leftToothId": 17, "rightToothId": 16, "dynamicDesign": null, "color": null, "findings": [] },
    { "id": 3100002, "leftToothId": 16, "rightToothId": 15, "dynamicDesign": null, "color": null, "findings": [] },
    { "id": 3100003, "leftToothId": 15, "rightToothId": 14, "dynamicDesign": null, "color": null, "findings": [] },
    { "id": 3100004, "leftToothId": 14, "rightToothId": 13, "dynamicDesign": null, "color": null, "findings": [] },
    { "id": 3100005, "leftToothId": 13, "rightToothId": 12, "dynamicDesign": null, "color": null, "findings": [] },
    { "id": 3100006, "leftToothId": 12, "rightToothId": 11, "dynamicDesign": null, "color": null, "findings": [] },
    { "id": 3100007, "leftToothId": 11, "rightToothId": 21, "dynamicDesign": null, "color": null, "findings": [] },
    { "id": 3100008, "leftToothId": 21, "rightToothId": 22, "dynamicDesign": null, "color": null, "findings": [] },
    { "id": 3100009, "leftToothId": 22, "rightToothId": 23, "dynamicDesign": null, "color": null, "findings": [] },
    { "id": 3100010, "leftToothId": 23, "rightToothId": 24, "dynamicDesign": null, "color": null, "findings": [] },
    { "id": 3100011, "leftToothId": 24, "rightToothId": 25, "dynamicDesign": null, "color": null, "findings": [] },
    { "id": 3100012, "leftToothId": 25, "rightToothId": 26, "dynamicDesign": null, "color": null, "findings": [] },
    { "id": 3100013, "leftToothId": 26, "rightToothId": 27, "dynamicDesign": null, "color": null, "findings": [] },
    { "id": 3100014, "leftToothId": 27, "rightToothId": 28, "dynamicDesign": null, "color": null, "findings": [] }
  ],
  "intermediateSpaceOnTheCanvasOfFinding32": [
    { "id": 3200000, "leftToothId": 18, "rightToothId": 17, "dynamicDesign": null, "color": null, "findings": [] },
    { "id": 3200001, "leftToothId": 17, "rightToothId": 16, "dynamicDesign": null, "color": null, "findings": [] },
    { "id": 3200002, "leftToothId": 16, "rightToothId": 15, "dynamicDesign": null, "color": null, "findings": [] },
    { "id": 3200003, "leftToothId": 15, "rightToothId": 14, "dynamicDesign": null, "color": null, "findings": [] },
    { "id": 3200004, "leftToothId": 14, "rightToothId": 13, "dynamicDesign": null, "color": null, "findings": [] },
    { "id": 3200005, "leftToothId": 13, "rightToothId": 12, "dynamicDesign": null, "color": null, "findings": [] },
    { "id": 3200006, "leftToothId": 12, "rightToothId": 11, "dynamicDesign": null, "color": null, "findings": [] },
    { "id": 3200007, "leftToothId": 11, "rightToothId": 21, "dynamicDesign": null, "color": null, "findings": [] },
    { "id": 3200008, "leftToothId": 21, "rightToothId": 22, "dynamicDesign": null, "color": null, "findings": [] },
    { "id": 3200009, "leftToothId": 22, "rightToothId": 23, "dynamicDesign": null, "color": null, "findings": [] },
    { "id": 3200010, "leftToothId": 23, "rightToothId": 24, "dynamicDesign": null, "color": null, "findings": [] },
    { "id": 3200011, "leftToothId": 24, "rightToothId": 25, "dynamicDesign": null, "color": null, "findings": [] },
    { "id": 3200012, "leftToothId": 25, "rightToothId": 26, "dynamicDesign": null, "color": null, "findings": [] },
    { "id": 3200013, "leftToothId": 26, "rightToothId": 27, "dynamicDesign": null, "color": null, "findings": [] },
    { "id": 3200014, "leftToothId": 27, "rightToothId": 28, "dynamicDesign": null, "color": null, "findings": [] }
  ],
  "intermediateSpaceOnTheCanvasOfFinding39": [
    { "id": 3900000, "leftToothId": 18, "rightToothId": 17, "dynamicDesign": null, "color": null, "findings": [] },
    { "id": 3900001, "leftToothId": 17, "rightToothId": 16, "dynamicDesign": null, "color": null, "findings": [] },
    { "id": 3900002, "leftToothId": 16, "rightToothId": 15, "dynamicDesign": null, "color": null, "findings": [] },
    { "id": 3900003, "leftToothId": 15, "rightToothId": 14, "dynamicDesign": null, "color": null, "findings": [] },
    { "id": 3900004, "leftToothId": 14, "rightToothId": 13, "dynamicDesign": null, "color": null, "findings": [] },
    { "id": 3900005, "leftToothId": 13, "rightToothId": 12, "dynamicDesign": null, "color": null, "findings": [] },
    { "id": 3900006, "leftToothId": 12, "rightToothId": 11, "dynamicDesign": null, "color": null, "findings": [] },
    { "id": 3900007, "leftToothId": 11, "rightToothId": 21, "dynamicDesign": null, "color": null, "findings": [] },
    { "id": 3900008, "leftToothId": 21, "rightToothId": 22, "dynamicDesign": null, "color": null, "findings": [] },
    { "id": 3900009, "leftToothId": 22, "rightToothId": 23, "dynamicDesign": null, "color": null, "findings": [] },
    { "id": 3900010, "leftToothId": 23, "rightToothId": 24, "dynamicDesign": null, "color": null, "findings": [] },
    { "id": 3900011, "leftToothId": 24, "rightToothId": 25, "dynamicDesign": null, "color": null, "findings": [] },
    { "id": 3900012, "leftToothId": 25, "rightToothId": 26, "dynamicDesign": null, "color": null, "findings": [] },
    { "id": 3900013, "leftToothId": 26, "rightToothId": 27, "dynamicDesign": null, "color": null, "findings": [] },
    { "id": 3900014, "leftToothId": 27, "rightToothId": 28, "dynamicDesign": null, "color": null, "findings": [] }
  ]
}
